nbp/NBPSolver.py
nbp/__init__.py
hynbp-0.0.3.dist-info/LICENSE
hynbp-0.0.3.dist-info/METADATA
hynbp-0.0.3.dist-info/WHEEL
hynbp-0.0.3.dist-info/top_level.txt
hynbp-0.0.3.dist-info/RECORD
