Metadata-Version: 2.1
Name: hynbp
Version: 0.0.3
Summary: Simple solution implementation of the N Body Problem of Physics
Home-page: https://github.com/J-angelm/hy-nbp
Author: J.Angel
Author-email: jorgeangel.mn@gmail.com
License: UNKNOWN
Platform: UNKNOWN
Classifier: Programming Language :: Python :: 3
Classifier: License :: OSI Approved :: MIT License
Classifier: Operating System :: OS Independent
Requires-Python: >=3.6
